README.rst
bootstrap.py
buildout.cfg
development.ini
pre-commit-check.sh
setup.cfg
setup.py
versions.cfg
docs/HISTORY.rst
docs/LICENSE.rst
docs/README.rst
docs/svnignore
docs/sphinx/api.rst
docs/sphinx/conf.py
docs/sphinx/glossary.rst
docs/sphinx/hours.bmml
docs/sphinx/hours.png
docs/sphinx/index.rst
docs/sphinx/settings.bmml
docs/sphinx/settings.png
docs/sphinx/tickets.bmml
docs/sphinx/tickets.png
docs/sphinx/ui.rst
src/multitrac/__init__.py
src/multitrac/date.py
src/multitrac/models.py
src/multitrac/tests.py
src/multitrac/trac.py
src/multitrac/version.txt
src/multitrac/views.py
src/multitrac.egg-info/PKG-INFO
src/multitrac.egg-info/SOURCES.txt
src/multitrac.egg-info/dependency_links.txt
src/multitrac.egg-info/entry_points.txt
src/multitrac.egg-info/not-zip-safe
src/multitrac.egg-info/requires.txt
src/multitrac.egg-info/top_level.txt
src/multitrac/static/favicon.ico
src/multitrac/static/footerbg.png
src/multitrac/static/headerbg.png
src/multitrac/static/ie6.css
src/multitrac/static/middlebg.png
src/multitrac/static/multitrac.css
src/multitrac/static/pylons.css
src/multitrac/static/pyramid-small.png
src/multitrac/static/pyramid.png
src/multitrac/static/transparent.gif
src/multitrac/templates/hours.pt
src/multitrac/templates/master.pt
src/multitrac/templates/root.pt
src/multitrac/templates/settings.pt
src/multitrac/templates/tickets.pt